codepress/VERSION
codepress/__init__.py
codepress/cli.py
codepress/version.py
codepress/vizualize.py
codepress-0.2.2.dist-info/LICENSE
codepress-0.2.2.dist-info/METADATA
codepress-0.2.2.dist-info/WHEEL
codepress-0.2.2.dist-info/entry_points.txt
codepress-0.2.2.dist-info/RECORD
