Metadata-Version: 2.3
Name: codepress
Version: 0.2.2
Summary: Transforming code into clean, readable text with precision and style.
License: MIT
Author: Allen Chou
Author-email: f1470891079@gmail.com
Requires-Python: >=3.11,<4
Classifier: License :: OSI Approved :: MIT License
Classifier: Programming Language :: Python :: 3
Classifier: Programming Language :: Python :: 3.11
Classifier: Programming Language :: Python :: 3.12
Classifier: Programming Language :: Python :: 3.13
Provides-Extra: all
Requires-Dist: click
Requires-Dist: jinja2
Requires-Dist: logging-bullet-train
Requires-Dist: pathspec
Requires-Dist: puremagic
Requires-Dist: tiktoken (>=0.9,<1) ; extra == "all"
Project-URL: Repository, https://github.com/allen2c/codepress
